fillbass/__init__.py
fillbass/entities.py
fillbass/fetchdata.py
fillbass/parsedata.py
fillbass/rest.py
fillbass/scripts/__init__.py
fillbass/scripts/scripts.py
fillbass-1.2.0.dist-info/DESCRIPTION.rst
fillbass-1.2.0.dist-info/METADATA
fillbass-1.2.0.dist-info/RECORD
fillbass-1.2.0.dist-info/WHEEL
fillbass-1.2.0.dist-info/entry_points.txt
fillbass-1.2.0.dist-info/metadata.json
fillbass-1.2.0.dist-info/top_level.txt
